persephone/__init__.py
persephone/config.py
persephone/context_manager.py
persephone/corpus.py
persephone/corpus_reader.py
persephone/distance.py
persephone/exceptions.py
persephone/experiment.py
persephone/logging.ini
persephone/model.py
persephone/results.py
persephone/rnn_ctc.py
persephone/utils.py
persephone/utterance.py
persephone/datasets/__init__.py
persephone/datasets/bkw.py
persephone/datasets/na.py
persephone/preprocess/__init__.py
persephone/preprocess/elan.py
persephone/preprocess/feat_extract.py
persephone/preprocess/labels.py
persephone/preprocess/pangloss.py
persephone/preprocess/wav.py
persephone-0.4.2.dist-info/LICENSE
persephone-0.4.2.dist-info/METADATA
persephone-0.4.2.dist-info/WHEEL
persephone-0.4.2.dist-info/top_level.txt
persephone-0.4.2.dist-info/RECORD
