Metadata-Version: 2.1
Name: persephone
Version: 0.4.2
Summary: A tool for developing automatic phoneme transcription models
Home-page: https://github.com/oadams/persephone
Author: Oliver Adams
Author-email: oliver.adams@gmail.com
License: GPLv3
Keywords: speech-recognition machine-learning acoustic-models artificial-intelligence neural-networks
Platform: UNKNOWN
Classifier: Development Status :: 4 - Beta
Classifier: Intended Audience :: Developers
Classifier: Programming Language :: Python
Classifier: Programming Language :: Python :: 3.6
Classifier: Programming Language :: Python :: 3.7
Requires-Dist: nltk (==3.4.5)
Requires-Dist: numpy (<2,>=1.14.5)
Requires-Dist: python-speech-features (==0.6)
Requires-Dist: scipy (<2,>=1.1.0)
Requires-Dist: tensorflow (<2,>=1.13.1)
Requires-Dist: scikit-learn (==0.21.2)
Requires-Dist: pympi-ling (==1.69)
Requires-Dist: pydub (==0.20.0)
Requires-Dist: pint (==0.9)
